blog/__init__.py
blog/admin.py
blog/apps.py
blog/signals.py
blog/token.py
blog/urls.py
blog/api/__init__.py
blog/api/v1/__init__.py
blog/api/v1/routers/__init__.py
blog/api/v1/routers/routers.py
blog/api/v1/serializers/__init__.py
blog/api/v1/serializers/article_serializers.py
blog/api/v1/serializers/author_serializers.py
blog/api/v1/serializers/category_serializers.py
blog/api/v1/serializers/comment_serializers.py
blog/api/v1/views/__init__.py
blog/api/v1/views/article_views.py
blog/api/v1/views/author_views.py
blog/api/v1/views/category_views.py
blog/api/v1/views/comment_views.py
blog/forms/__init__.py
blog/forms/account/__init__.py
blog/forms/account/login_forms.py
blog/forms/account/register_forms.py
blog/forms/blog/__init__.py
blog/forms/blog/article_forms.py
blog/forms/blog/category_forms.py
blog/forms/blog/comment_forms.py
blog/forms/dashboard/__init__.py
blog/forms/dashboard/author/__init__.py
blog/forms/dashboard/author/author_forms.py
blog/migrations/0001_initial.py
blog/migrations/0002_auto_20200618_2226.py
blog/migrations/0003_auto_20200618_2322.py
blog/migrations/0004_article_deleted.py
blog/migrations/0005_comment_approved.py
blog/migrations/0006_auto_20200625_1909.py
blog/migrations/0007_auto_20200626_0338.py
blog/migrations/0008_auto_20200626_1433.py
blog/migrations/0009_article_image_credit.py
blog/migrations/0010_auto_20200704_1648.py
blog/migrations/0011_auto_20200704_1656.py
blog/migrations/__init__.py
blog/models/__init__.py
blog/models/article_models.py
blog/models/author_models.py
blog/models/category_models.py
blog/models/comment_models.py
blog/templatetags/__init__.py
blog/templatetags/only_hours.py
blog/templatetags/urlify.py
blog/tests/__init__.py
blog/tests/forms/__init__.py
blog/tests/forms/test_comment_forms.py
blog/tests/models/__init__.py
blog/tests/models/test_article_models.py
blog/tests/models/test_author_models.py
blog/tests/models/test_category_models.py
blog/tests/models/test_comment_models.py
blog/tests/views/__init__.py
django_bona_blog-1.1.4.dist-info/LICENSE
django_bona_blog-1.1.4.dist-info/METADATA
django_bona_blog-1.1.4.dist-info/WHEEL
django_bona_blog-1.1.4.dist-info/top_level.txt
django_bona_blog-1.1.4.dist-info/RECORD
