Metadata-Version: 2.1
Name: django-bona-blog
Version: 1.1.4
Summary: A Django blog app with features of a standard blogging platform.
Home-page: https://github.com/Williano/django-bona-blog
Author: William Kpabitey Kwabla (fork author)
Author-email: paawilly17@gmail.com
License: MIT License
Keywords: django-blogging django django-app django-blog-app django-blog
Platform: any
Classifier: Development Status :: 5 - Production/Stable
Classifier: Environment :: Web Environment
Classifier: Framework :: Django
Classifier: Intended Audience :: Developers
Classifier: License :: OSI Approved :: MIT License
Classifier: Operating System :: OS Independent
Classifier: Framework :: Django
Classifier: Framework :: Django :: 2.2
Classifier: Framework :: Django :: 3.0
Classifier: Programming Language :: Python
Classifier: Programming Language :: Python :: 3
Classifier: Programming Language :: Python :: 3.6
Classifier: Programming Language :: Python :: 3.7
Classifier: Programming Language :: Python :: 3.8
Classifier: Framework :: Django
Classifier: Topic :: Software Development :: Libraries :: Application Frameworks
Classifier: Topic :: Software Development :: Libraries :: Python Modules
Requires-Python: >=3.6
Requires-Dist: Django (>=2.2)
Requires-Dist: six
Requires-Dist: Pillow
Requires-Dist: django-ckeditor
Requires-Dist: django-filter
Requires-Dist: django-taggit
Requires-Dist: djangorestframework
Requires-Dist: django-crispy-forms
